simple_flask_cms/__init__.py
simple_flask_cms/cms.py
simple_flask_cms/cms_blueprint.py
simple_flask_cms/config.py
simple_flask_cms/dataclasses.py
simple_flask_cms/db.py
simple_flask_cms/fragments.py
simple_flask_cms/render.py
simple_flask_cms/database_providers/__init__.py
simple_flask_cms/database_providers/sql_database.py
simple_flask_cms/static/editor.css
simple_flask_cms/static/icon.svg
simple_flask_cms/static/generated/editor.css
simple_flask_cms/static/generated/editor.js
simple_flask_cms/static/generated/fragment.js
simple_flask_cms/static/generated/overview.js
simple_flask_cms/templates/cms/404.html
simple_flask_cms/templates/cms/editor.html
simple_flask_cms/templates/cms/fragment.html
simple_flask_cms/templates/cms/images.html
simple_flask_cms/templates/cms/main.html
simple_flask_cms/templates/cms/overview.html
simple_flask_cms/templates/cms/recursive_nav.html
simple_flask_cms/templates/cms/sidebar.html
simple_flask_cms/templates/cms/example_templates/nav.html
simple_flask_cms/templates/cms/example_templates/page.html
simple_flask_cms-0.0.14.dist-info/METADATA
simple_flask_cms-0.0.14.dist-info/WHEEL
simple_flask_cms-0.0.14.dist-info/top_level.txt
simple_flask_cms-0.0.14.dist-info/RECORD
