Metadata-Version: 2.1
Name: simple-flask-cms
Version: 0.0.14
Summary: A minimal CMS for flask
Home-page: https://gitlab.com/mousetail/simple-flask-cms
Author: Maurits van Riezen (mousetail)
Author-email: mousetail+pypi@mousetail.nl
License: GPL-2
Platform: UNKNOWN
Classifier: Programming Language :: Python :: 3
Classifier: Programming Language :: Python :: 3.9
Classifier: Development Status :: 4 - Beta
Classifier: Framework :: Flask
Classifier: License :: OSI Approved :: GNU General Public License v3 (GPLv3)
